PyDAIR/__init__.py
PyDAIR/app/PyDAIRAPP.py
PyDAIR/app/__init__.py
PyDAIR/bin/pydair
PyDAIR/io/PyDAIRIO.py
PyDAIR/io/PyDAIRReport.py
PyDAIR/io/__init__.py
PyDAIR/plot/PyDAIRPlot.py
PyDAIR/plot/__init__.py
PyDAIR/seq/IgSeq.py
PyDAIR/seq/__init__.py
PyDAIR/sim/PyDAIRSim.py
PyDAIR/sim/__init__.py
PyDAIR/stats/PyDAIRStats.py
PyDAIR/stats/__init__.py
PyDAIR/templates/report.google.html
PyDAIR/templates/report.html
PyDAIR/utils/PyDAIRArgs.py
PyDAIR/utils/PyDAIRUtils.py
PyDAIR/utils/__init__.py
PyDAIR-0.1.14.data/scripts/pydair
PyDAIR-0.1.14.dist-info/DESCRIPTION.rst
PyDAIR-0.1.14.dist-info/METADATA
PyDAIR-0.1.14.dist-info/RECORD
PyDAIR-0.1.14.dist-info/WHEEL
PyDAIR-0.1.14.dist-info/metadata.json
PyDAIR-0.1.14.dist-info/top_level.txt
PyDAIR-0.1.14.dist-info/zip-safe
