Metadata-Version: 2.0
Name: PyDAIR
Version: 0.1.14
Summary: Python library for diversity analysis of immune repertoire
Home-page: https://biunit.org/pydair
Author: biunit
Author-email: pydair@biunit.org
License: GNU
Keywords: blast,bioinformatics
Platform: UNKNOWN
Classifier: Development Status :: 5 - Production/Stable
Classifier: Environment :: Console
Classifier: Intended Audience :: Science/Research
Classifier: Natural Language :: English
Classifier: Operating System :: OS Independent
Classifier: Programming Language :: Python :: 2.7
Classifier: Programming Language :: Python :: 3
Classifier: Topic :: Scientific/Engineering :: Bio-Informatics
Classifier: License :: OSI Approved :: GNU General Public License v2 (GPLv2)
Requires-Dist: biopython
Requires-Dist: jinja2
Requires-Dist: matplotlib (>=1.4)
Requires-Dist: pandas
